{
  "sites": [
    {
      "name": "Zamboanga City Port",
      "lat": 6.902949,
      "lon": 122.073857,
      "status": "Completed",
      "year started": "1831",
      "year completed": "2025",
      "developer": "Local residents/establishments/LGU",
      "author": "AGF",
      "notes": "With on-going government projects",
      "barangay": "Barangay Zone 3 Poblacion",
      "municipality": "Zamboanga City",
      "province": "Zamboanga del Sur",
      "region": "Region 9",
      "address": "Barangay Zone 3 Poblacion, Zamboanga City, Zamboanga del Sur",
      "photos": [
        "https://lh3.googleusercontent.com/d/1T-R4mUAWCoS9ktpFT7zFcXvZulrSPHfW"
      ],
      "polygon": [
        [6.906, 122.069],
        [6.906, 122.079],
        [6.900, 122.079],
        [6.900, 122.069]
      ]
    },
    {
      "name": "Paseo del Mar",
      "lat": 6.900461,
      "lon": 122.08124,
      "status": "Completed",
      "year started": "N/A",
      "year completed": "2009",
      "developer": "Zamboanga City LGU",
      "author": "AGF",
      "notes": "Recreation space launched in 2009 by the LGU",
      "barangay": "Barangay Zone 3 Poblacion",
      "municipality": "Zamboanga City",
      "province": "Zamboanga del Sur",
      "region": "Region 9",
      "address": "Barangay Zone 3 Poblacion, Zamboanga City, Zamboanga del Sur",
      "photos": [
        "https://lh3.googleusercontent.com/d/1bhRPsGrdKn3KkmezH3-YkyK4MBkG873t"
      ],
      "polygon": [
        [6.902, 122.079],
        [6.902, 122.084],
        [6.898, 122.084],
        [6.898, 122.079]
      ]
    },
    {
      "name": "Hamilo Coast Terminal",
      "lat": 14.18249,
      "lon": 120.601914,
      "status": "Completed",
      "year started": "pre-2010",
      "year completed": "2013",
      "developer": "Local residents/establishments",
      "author": "AGF",
      "notes": "Potruding small boat port",
      "barangay": "Papaya",
      "municipality": "Nasugbu",
      "province": "Batangas",
      "region": "IV-A CALABARZON",
      "address": "Papaya, Nasugbu, Batangas",
      "photos": [
        "https://lh3.googleusercontent.com/d/1YA7DrFY6VibY6DfAuUVICfN5ECefDY6P",
        "https://lh3.googleusercontent.com/d/1TOtMVVMZkL3-movH1j4ZyRudqFfMf80h"
      ]
    },
    {
      "name": "Papaya Cove Ports",
      "lat": 14.175632,
      "lon": 120.606667,
      "status": "On-Going",
      "year started": "pre-2010",
      "year completed": "N/A",
      "developer": "Local residents/establishments/LGU",
      "author": "AGF",
      "notes": "Started before 1985 (Google Earth Limit)",
      "barangay": "Papaya",
      "municipality": "Nasugbu",
      "province": "Batangas",
      "region": "IV-A CALABRZON",
      "address": "Papaya, Nasugbu, Batangas",
      "photos": [
        "https://lh3.googleusercontent.com/d/1dWAdVul_F3p33icQn9cJpIdAYD0r0-CA",
        "https://lh3.googleusercontent.com/d/1vaH1oeTlD1Iard1RWGJCjXSpXe-C_-6E"
      ]
    },
    {
      "name": "Papaya Cove Resorts",
      "lat": 14.174311,
      "lon": 120.604036,
      "status": "completed",
      "year started": "2018",
      "year completed": "2024",
      "developer": "Local residents/establishments",
      "author": "AGF",
      "notes": "Development of a residential/resort area beyond the shoreline of a sandy beach area",
      "barangay": "Papaya",
      "municipality": "Nasugbu",
      "province": "Batangas",
      "region": "IV-A CALABARZON",
      "address": "Papaya, Nasugbu, Batangas",
      "photos": [
        "https://lh3.googleusercontent.com/d/1KKkdrn0vmK_hU0B-bOevS6t9RQNIfDCA",
        "https://lh3.googleusercontent.com/d/11qeQJvhj2YSfANa8zArg-WRwlFubLxOn",
        "https://lh3.googleusercontent.com/d/16olQDO5-tB7VILvq76hujAzU5mJfSFnP"
      ]
    },
    {
      "name": "Samal",
      "lat": 7.071214,
      "lon": 125.709203,
      "status": "ongoing",
      "year started": "2010",
      "year completed": "2015",
      "developer": "Philippine Reclamation Authority",
      "author": "CLSA",
      "notes": "",
      "barangay": "Peñaplata",
      "municipality": "Island City of Samal",
      "province": "Davao del Norte",
      "region": "Davao Region",
      "address": "Peñaplata, Island City of Samal, Davao del Norte",
      "photos": [
        "https://lh3.googleusercontent.com/d/1HTxqGCbIteLdL_wttHjktxCVm8gr5g5M",
        "https://lh3.googleusercontent.com/d/11r2f57lxiPd8QP6xj8hDImX9Y3W2rCzE",
        "https://lh3.googleusercontent.com/d/1SJ_RB1lUXN8kTm9FxW8w6-qLTG93u5hz",
        "https://lh3.googleusercontent.com/d/1bS48mRj2htTk7wlbmyWLSlTMA1ByynLn"
      ]
    },
    {
      "name": "Mariveles Power Generaton Corporation",
      "lat": 14.446785,
      "lon": 120.433437,
      "status": "completed",
      "year started": "2020",
      "year completed": "2025",
      "developer": "Mariveles Power Generation Corporation",
      "author": "CLSA",
      "notes": "Cut and fill and eventual shoreline extension for additional land area of the port/harbor area; built on sand",
      "barangay": "Biaan",
      "municipality": "Mariveles",
      "province": "Bataan",
      "region": "Central Luzon",
      "address": "Biaan, Mariveles, Bataan",
      "photos": [
        "https://lh3.googleusercontent.com/d/1R75z-39LmCGaypegC5jIldsLGyjmnCZF",
        "https://lh3.googleusercontent.com/d/1RdKcvStbQDlsC4HH4CNtMpg8iRTmH_E1",
        "https://lh3.googleusercontent.com/d/1LvrFThbztLQ2Qw3IHJo_QsfuX2j1kg0Q",
        "https://lh3.googleusercontent.com/d/1_7dTGyH-RH5m324BqneHvwlJjuQedUuN"
      ]
    },
    {
      "name": "Mariveles Harbor Corporation",
      "lat": 14.428371,
      "lon": 120.51236,
      "status": "completed",
      "year started": "2014",
      "year completed": "2019",
      "developer": "Mariveles Harbor Corporation?",
      "author": "CLSA",
      "notes": "Extended land area with harbor; built on sand",
      "barangay": "Sisiman",
      "municipality": "Mariveles",
      "province": "Bataan",
      "region": "Central Luzon",
      "address": "Sisiman, Mariveles, Bataan",
      "photos": [
        "https://lh3.googleusercontent.com/d/1m636y3z5POznOXgGwwV7cJxsBaGG7yD-",
        "https://lh3.googleusercontent.com/d/17pt1iCsoErlSjorI9sGg5tCMlFpwBqHJ",
        "https://lh3.googleusercontent.com/d/1YbdebkSUpMuqXhs1h6IpLKicXVgIFZah",
        "https://lh3.googleusercontent.com/d/1SvaqwfhLBcOCnzLDB8vay_2DvsHk8AjZ"
      ]
    },
    {
      "name": "Planters Aggregates, Inc.",
      "lat": 14.428168,
      "lon": 120.527366,
      "status": "ongoing",
      "year started": "2022",
      "year completed": "2025",
      "developer": "Planters Aggregates, Inc.",
      "author": "CLSA",
      "notes": "Extended shoreline for additional land area; built on sand",
      "barangay": "Sisiman",
      "municipality": "Mariveles",
      "province": "Bataan",
      "region": "Central Luzon",
      "address": "Sisiman, Mariveles, Bataan",
      "photos": [
        "https://lh3.googleusercontent.com/d/1WxQesvtoqkO0cmIkWauS3BMS84cou1HQ",
        "https://lh3.googleusercontent.com/d/1-Pr017PVW_B6WmUAvmQ4IrsT3ZVdiXSr",
        "https://lh3.googleusercontent.com/d/1QzxiMNV9BlWhLewqe_nBDgRgCAC3hTob",
        "https://lh3.googleusercontent.com/d/15SACFb2_brUJ73i0hcY_pdYYEjiub_Bt"
      ]
    },
    {
      "name": "Premium Megastructures, Inc. (?)",
      "lat": 14.421782,
      "lon": 120.554333,
      "status": "completed",
      "year started": "2021",
      "year completed": "2025",
      "developer": "n/a",
      "author": "CLSA",
      "notes": "Shoreline extension; built on sand",
      "barangay": "Alas-asin",
      "municipality": "Mariveles",
      "province": "Bataan",
      "region": "Central Luzon",
      "address": "Alas-asin, Mariveles, Bataan",
      "photos": [
        "https://lh3.googleusercontent.com/d/1JErZnJVLG7L_-2Hy6-Vf4URl9R_Kplew",
        "https://lh3.googleusercontent.com/d/1aUw3IZLD-oCPCV18P8ZVZ_x0X7G7LYnW",
        "https://lh3.googleusercontent.com/d/1zJ3rdl0ZsH1q0I-EFFCzXD08bXSzLuaq",
        "https://lh3.googleusercontent.com/d/1nIiKMQGc6vSOTUn5TcQB9O55aMaaM99r"
      ]
    },
    {
      "name": "Seafront Townsite Bataan",
      "lat": 14.458137,
      "lon": 120.600912,
      "status": "completed",
      "year started": "2017",
      "year completed": "2024",
      "developer": "Seafront Shipyard and Port Terminal Services, Inc.",
      "author": "CLSA",
      "notes": "For construction of main RC pier and trestle and construction of 20-hectare back-up area; built on sand",
      "barangay": "Townsite",
      "municipality": "Mariveles",
      "province": "Bataan",
      "region": "Central Luzon",
      "address": "Townsite, Mariveles, Bataan",
      "photos": [
        "https://lh3.googleusercontent.com/d/1_rtqlz0HTa2pOkL8ffHg-m02oYZq_23d",
        "https://lh3.googleusercontent.com/d/1aV6R3jH-CuKUxS72_RCdGCmmlnXeRX4T",
        "https://lh3.googleusercontent.com/d/1-hsB1XRVHlLs3gBz98_Fodifg3pPPhtn",
        "https://lh3.googleusercontent.com/d/1KWfO0jmF4S1DoxmsxEoYjdJ6xMwgxRPA"
      ]
    },
    {
      "name": "Limay Power Plant",
      "lat": 14.524311,
      "lon": 120.609093,
      "status": "completed",
      "year started": "2017",
      "year completed": "2024",
      "developer": "San Miguel Corporation",
      "author": "CLSA",
      "notes": "Built on sand",
      "barangay": "Alangan",
      "municipality": "Limay",
      "province": "Bataan",
      "region": "Central Luzon",
      "address": "Alangan, Limay, Bataan",
      "photos": [
        "https://lh3.googleusercontent.com/d/1q2vTtBoqdih91PLd2uK0wd264cUeHA9m",
        "https://lh3.googleusercontent.com/d/1Zf1yG_aWbD4q9GZLA6U2iiUVuZvpKL6x",
        "https://lh3.googleusercontent.com/d/1WfxPghAbD0h0rahwUi_F3aBW5m3ifdN-",
        "https://lh3.googleusercontent.com/d/1UxXJQF6Kw-tc_k8DK6Kg9O_abqp2txJQ"
      ]
    },
    {
      "name": "Limay Coastal Road/Park",
      "lat": 14.558599,
      "lon": 120.600067,
      "status": "ongoing",
      "year started": "2020",
      "year completed": "2025",
      "developer": "Limay LGU?",
      "author": "CLSA",
      "notes": "For coastal road/park; Built on sand",
      "barangay": "Landing",
      "municipality": "Limay",
      "province": "Bataan",
      "region": "Central Luzon",
      "address": "Landing, Limay, Bataan",
      "photos": [
        "https://lh3.googleusercontent.com/d/1E6HIWZGPj3GKir-5rKfA3ObCTrxoTr2M",
        "https://lh3.googleusercontent.com/d/1KiqPUUPSBKEfHQoC00UR9Dvyz9s4eNV1",
        "https://lh3.googleusercontent.com/d/131G6DTdg69lVtKQFpqbUuMoulKAmeUOS",
        "https://lh3.googleusercontent.com/d/1P8RHNYZVrNleeCJ3PgnekYJHwpkbOggn"
      ]
    },
    {
      "name": "Calayo Beach",
      "lat": 14.155026,
      "lon": 120.606244,
      "status": "Completed",
      "year started": "2013",
      "year completed": "2019",
      "developer": "Brgy Calayo Residents",
      "author": "AGF",
      "notes": "Dumping of materials at the mouth of a river opening into the sea then establised buildings and houses in the area.",
      "barangay": "Calayo",
      "municipality": "Nasugbu",
      "province": "Batangas",
      "region": "IV-A CALABARZON",
      "address": "Calayo, Nasugbu, Batangas",
      "photos": [
        "https://lh3.googleusercontent.com/d/1gpFPajXnGVkO5PPYkcpfHrXlrdHbQ1_E",
        "https://lh3.googleusercontent.com/d/1DBmXrTDDNgwnEoRHYa8tTIkeSE-Un_uW",
        "https://lh3.googleusercontent.com/d/1GL1hC96oB_ftAWeILb8t-FL0I0Mqb8c3"
      ]
    },
    {
      "name": "Lapaspas Campsite",
      "lat": 14.022881,
      "lon": 120.619014,
      "status": "Ongoing",
      "year started": "2021",
      "year completed": "N/A",
      "developer": "Lapaspas Campsite?",
      "author": "AGF",
      "notes": "Dumping of materials beyond the shoreline of a beach and placing a building on it.",
      "barangay": "San Diego",
      "municipality": "Lian",
      "province": "Batangas",
      "region": "IV-A CALABARZON",
      "address": "San Diego, Lian, Batangas",
      "photos": [
        "https://lh3.googleusercontent.com/d/1JDir-R1sx8jEf5k5_fFfhtKcD_E6k_Hg",
        "https://lh3.googleusercontent.com/d/1sIlgKMR74fjQDcDl6osVpEkjk5K3oxPP",
        "https://lh3.googleusercontent.com/d/11LNxWdmJ0ZUV0h6mLDfqIWFqKYxpGwGJ"
      ]
    },
    {
      "name": "Matabungakay Beach Resorts",
      "lat": 13.936028,
      "lon": 120.617176,
      "status": "Ongoing",
      "year started": "pre-2010",
      "year completed": "N/A",
      "developer": "Local Resort Owners",
      "author": "AGF",
      "notes": "Outbuilding of beach resorts off the shorelines of Matabungkay Beach. (Golden Sea Beach Resort, The Lavana Villa Del Matabungkay Private Resort Batangas by RedDoorz, Hidden Reef Beach Resort, Jupiter Beach Resort Hotel And Restaurant, Seamaster Beach Resort, Villa Antonio Matabungkay, Sea Star beach club, JRC Breeze Beach Resort)",
      "barangay": "Matabungkay",
      "municipality": "Lian",
      "province": "Batangas",
      "region": "IV-A CALABARZON",
      "address": "Matabungkay, Lian, Batangas",
      "photos": [
        "https://lh3.googleusercontent.com/d/1EIncSzxZzJLr8ZQQfSSiZGcIHHz5Kycc",
        "https://lh3.googleusercontent.com/d/1lpbBczFwt5YQQoiS5djQpgRIZgxn_01v"
      ]
    },
    {
      "name": "Natipuan Beach Marina",
      "lat": 14.115984,
      "lon": 120.612316,
      "status": "Completed",
      "year started": "Pre-1990",
      "year completed": "Pre-2010",
      "developer": "Local Resort Owners (?)",
      "author": "AGF",
      "notes": "A small marina located along the Natipuan Beach filled with small yachts. Area was built sometime between 1990-2010 (google earth limit).",
      "barangay": "Natipuan",
      "municipality": "Nasugbu",
      "province": "Batangasn",
      "region": "IV-A CALABAZON",
      "address": "Natipuan, Nasugbu, Batangasn",
      "photos": [
        "https://lh3.googleusercontent.com/d/1c6_sR9fciMC2W2acS-l29Z8r0jw_qW2U",
        "https://lh3.googleusercontent.com/d/1tllJDGW_N-S2XPVheHBHS_of2GTOkYmP"
      ]
    },
    {
      "name": "Asahi Electrical Manufacturing",
      "lat": 14.534974,
      "lon": 121.114375,
      "status": "Completed",
      "year started": "2014",
      "year completed": "2024",
      "developer": "Asahi Electrical Manufacturing Corporation",
      "author": "AGF",
      "notes": "Dumped materials and built storage facilities on a previous flooded farmland.",
      "barangay": "San Juan",
      "municipality": "Taytay",
      "province": "Rizal",
      "region": "IV-A CALABARZON",
      "address": "San Juan, Taytay, Rizal",
      "photos": [
        "https://lh3.googleusercontent.com/d/1yGCHZ2bLapEabt6ceGjgg-jdwBLapMQa",
        "https://lh3.googleusercontent.com/d/1WMOQ6HCXjHFECQqNwIaWbQpUBCLkDtkj",
        "https://lh3.googleusercontent.com/d/16-ZYwhcFp56-eE6ustUFXlMeZGiGiPDN"
      ]
    },
    {
      "name": "Laguna de Bay (Calzada)",
      "lat": 14.525159,
      "lon": 121.091002,
      "status": "Ongoing",
      "year started": "2014",
      "year completed": "N/A",
      "developer": "IPM Construction and Development Corporation and Level Up Construction and Development Corporation",
      "author": "AGF",
      "notes": "Laguna de Bay area along C6 road has been dumped with landfiill by two contractors. Illegal reclamation of bay area that was later occupied by several local establishments.Previously a swamp area",
      "barangay": "Palingon, Calzada, Santa Ana",
      "municipality": "Taguig",
      "province": "Metro Manila",
      "region": "NCR",
      "address": "Palingon, Calzada, Santa Ana, Taguig, Metro Manila",
      "photos": [
        "https://lh3.googleusercontent.com/d/1hi4opQXURKIE8KyaSYYd_2C7U1TtSmYH",
        "https://lh3.googleusercontent.com/d/1In5IcTSlMwJJ9rdX0Z2gf9pbh-9RaTbT",
        "https://lh3.googleusercontent.com/d/1d7KheNa9L9XJoweucSfrUWy9FsC3i_xT"
      ]
    },
    {
      "name": "Laguna de Bay (Hangonoy)",
      "lat": 14.508771,
      "lon": 121.072303,
      "status": "Ongoing",
      "year started": "2012",
      "year completed": "N/A",
      "developer": "",
      "author": "AGF",
      "notes": "Laguna de Bay area that has gone under reclamation now filled with residents and establishments",
      "barangay": "Hangonoy & New Lower Bicutan",
      "municipality": "Taguig City",
      "province": "Metro Manilan",
      "region": "NCR",
      "address": "Hangonoy & New Lower Bicutan, Taguig City, Metro Manilan",
      "photos": [
        "https://lh3.googleusercontent.com/d/1NNgU1c0vT0R4dfa9Qjuyy3hjphs8SJil",
        "https://lh3.googleusercontent.com/d/1jzvszF1zdPkRjM98fj8xEestQGcKECOv",
        "https://lh3.googleusercontent.com/d/1jzD22C2RFiF3NLyUnqgktNTgjx9vbbIG"
      ]
    },
    {
      "name": "Laguna de Bay (Taguig Part - New Lower Bicutan)",
      "lat": 14.501319,
      "lon": 121.067556,
      "status": "Ongoing",
      "year started": "2022",
      "year completed": "N/A",
      "developer": "DPWH/New Big Four J Construction Inc.",
      "author": "AGF",
      "notes": "Multiple small-scalre reclamacation along the lakeshores of New Lower Bicutan disguised as a 70-million flood control project.",
      "barangay": "New Lower Bicutan",
      "municipality": "Taguig City",
      "province": "Metro Manila",
      "region": "NCR",
      "address": "New Lower Bicutan, Taguig City, Metro Manila",
      "photos": [
        "https://lh3.googleusercontent.com/d/1n6eOJmvSMidGpDvTH2S0No-3-kaAjhXf",
        "https://lh3.googleusercontent.com/d/1jY6U9BfQruNl3DYu7d4yF8I4HARMsMCO",
        "https://lh3.googleusercontent.com/d/1u3pQ7a5QWExt9R2ucZJYREy0hFhOaJS6"
      ]
    },
    {
      "name": "Taguig Lakeshore Community Park",
      "lat": 14.491348,
      "lon": 121.063849,
      "status": "Completed",
      "year started": "2012",
      "year completed": "2024",
      "developer": "Taguig City LGU",
      "author": "AGF",
      "notes": "A public theme park established along the lakeshores of Laguna de Bay in the Lower Bicutan Area",
      "barangay": "Lower Bicutan",
      "municipality": "Taguig City",
      "province": "Metro Manila",
      "region": "NCR",
      "address": "Lower Bicutan, Taguig City, Metro Manila",
      "photos": [
        "https://lh3.googleusercontent.com/d/1eOtdX9c3enOSnk9b2rdF2tRPzR2X4mlM",
        "https://lh3.googleusercontent.com/d/1mzFUytBUt7Al153ACgJXKxLScmuD6l6L",
        "https://lh3.googleusercontent.com/d/1UGXLprLZBF67U1SHj8VNopmocoSmede2"
      ]
    },
    {
      "name": "Laguna de Bay (Taguig Part - Lower Bicutan & Bagumbayan)",
      "lat": 14.484,
      "lon": 121.062556,
      "status": "Ongoing",
      "year started": "2010",
      "year completed": "N/A",
      "developer": "",
      "author": "AGF",
      "notes": "Lakeshore roads placed beyond the shores of Laguna de Bay along brgy. Lower Bicutan and Bagumbayan",
      "barangay": "Lower Bicutan & Bagumbayan",
      "municipality": "Taguig City",
      "province": "Metro Manila",
      "region": "NCR",
      "address": "Lower Bicutan & Bagumbayan, Taguig City, Metro Manila",
      "photos": [
        "https://lh3.googleusercontent.com/d/1o11bp8PYclTA9aX-bQKjP2jAkxBibDwh",
        "https://lh3.googleusercontent.com/d/1OfILASgV_mCD7zI0m8vdbWywjTQiXIOu",
        "https://lh3.googleusercontent.com/d/16CcyzxWRVgvPb28A5FuaEV1n_PE7qFGV"
      ]
    },
    {
      "name": "Laguna de Bay (Taguig part - Bagumbayan)",
      "lat": 14.47783,
      "lon": 121.061763,
      "status": "Ongoing",
      "year started": "Pre-2004",
      "year completed": "N/A",
      "developer": "Local Residents/Establishments",
      "author": "AGF",
      "notes": "Outbuilding of several residents and establishments lakewards through dumping of reclamation materials to extend the lakeshore.",
      "barangay": "Bagumbayan",
      "municipality": "Taguig City",
      "province": "Metro Manila",
      "region": "NCR",
      "address": "Bagumbayan, Taguig City, Metro Manila",
      "photos": [
        "https://lh3.googleusercontent.com/d/1uUybhFPoeizViXAW3ppRdSK3M4vzVSVP",
        "https://lh3.googleusercontent.com/d/1hNp-l-TJLpbazUJGy1Ia5z2wz8OBT4e3"
      ]
    },
    {
      "name": "Laguna de Bay (Taguig part - Bagumbayan 2)",
      "lat": 14.47006,
      "lon": 121.058603,
      "status": "Ongoing",
      "year started": "Pre-2004",
      "year completed": "N/A",
      "developer": "Local Residents/Establishments",
      "author": "AGF",
      "notes": "Outbuilding of several residents and establishments lakewards through dumping of reclamation materials to extend the lakeshore.",
      "barangay": "Bagumbayan",
      "municipality": "Taguig City",
      "province": "Metro manila",
      "region": "NCR",
      "address": "Bagumbayan, Taguig City, Metro manila",
      "photos": [
        "https://lh3.googleusercontent.com/d/1Br1onC-mQ_lNBbm2ogD4wb5CwTJO-CGw",
        "https://lh3.googleusercontent.com/d/1m9CiX-XrLk4dZSV9ZsqvnwuIC_-zWBVd"
      ]
    },
    {
      "name": "Wawa Pier",
      "lat": 14.082404,
      "lon": 120.620405,
      "status": "Completed",
      "year started": "1936",
      "year completed": "N/A",
      "developer": "Nasugbu LGU",
      "author": "AGF",
      "notes": "A small port potruding along the coasts of Barangay Wawa, Nasugbu, Batangas.",
      "barangay": "Wawa",
      "municipality": "Nasugbu",
      "province": "Batangas",
      "region": "IV-A Calabarzon",
      "address": "Wawa, Nasugbu, Batangas",
      "photos": [
        "https://lh3.googleusercontent.com/d/1NtlRutPXgbmsKF38cwTgHxZTj4YG71B6",
        "https://lh3.googleusercontent.com/d/1b35cePmT0mwITKZZNbkJ5kbPPJY8Qjyk"
      ]
    },
    {
      "name": "Club Punta Fuego Beach Marina",
      "lat": 14.131144,
      "lon": 120.589512,
      "status": "Completed",
      "year started": "1995",
      "year completed": "2003",
      "developer": "Roxaco Land Corporation and Landco Pacific Corporation",
      "author": "AGF",
      "notes": "A small marina located at a local beach club in Nasugbu, Batangas.",
      "barangay": "Balaytigui",
      "municipality": "Nasugbu",
      "province": "Batangas",
      "region": "IV-A Calabarzon",
      "address": "Balaytigui, Nasugbu, Batangas",
      "photos": [
        "https://lh3.googleusercontent.com/d/1e2SAqI8rB7-Tvt4BvfAmVGqxb0-G1fG_",
        "https://lh3.googleusercontent.com/d/1hhg8ClUA3RA8fZspK3atqh1Eb0uItLWd"
      ]
    },
    {
      "name": "Sucat People's Park",
      "lat": 14.456504,
      "lon": 121.054528,
      "status": "Completed",
      "year started": "2009",
      "year completed": "2012",
      "developer": "Muntinlupa LGU",
      "author": "AGF",
      "notes": "A public-themed park that was placed on reclaimed lands beyond the lakeshores of barangay Sucat, Muntinlupa City",
      "barangay": "Sucat",
      "municipality": "Muntinlupa City",
      "province": "Metro Manila",
      "region": "NCR",
      "address": "Sucat, Muntinlupa City, Metro Manila",
      "photos": [
        "https://lh3.googleusercontent.com/d/1JX8LKGcs26v1XbM8T1Ugq5KYfHw2W7Ix",
        "https://lh3.googleusercontent.com/d/1s-hXnJIRROMzgiA5_k_Ay2Lcp1aVaIuS",
        "https://lh3.googleusercontent.com/d/17W2CsY5L10Gxj5NX8vBqhftV1CX4KJor"
      ]
    },
    {
      "name": "NGCP Muntinlupa Lakeshore Area",
      "lat": 14.443625,
      "lon": 121.052884,
      "status": "Completed",
      "year started": "2010",
      "year completed": "2025",
      "developer": "Monte de Oro Grid Resources Corporation, Calaca High Power Corporation, State Grid Corporation of CN",
      "author": "AGF",
      "notes": "Land reclamation around the NGCP substation in the lakeshores of Laguna de Bay in barangay Buli, Muntinlupa City.",
      "barangay": "Buli",
      "municipality": "Muntinlupa City",
      "province": "Metro Manila",
      "region": "NCR",
      "address": "Buli, Muntinlupa City, Metro Manila",
      "photos": [
        "https://lh3.googleusercontent.com/d/1W1H99u8Mz82C96TrjvBaLpfWQYed_1nF",
        "https://lh3.googleusercontent.com/d/1bhRPsGrdKn3KkmezH3-YkyK4MBkG873t",
        "https://lh3.googleusercontent.com/d/1w4VS87DxBklfuke3bUp_rvWO03xpnSup"
      ]
    },
    {
      "name": "C6 Extension to Sucat Interchange East Service Road, Muntinlupa City",
      "lat": 14.460945,
      "lon": 121.05591,
      "status": "Ongoing",
      "year started": "2021",
      "year completed": "N/A",
      "developer": "DPWH, Le Bron Construction, I & E Construction Corporation, LMG Construction Inc.",
      "author": "AGF",
      "notes": "An extension of C6 road into the Sucat area as well as an access road where several contractors have been funded to build.",
      "barangay": "Sucat",
      "municipality": "Muntinlupa City",
      "province": "Metro Manila",
      "region": "NCR",
      "address": "Sucat, Muntinlupa City, Metro Manila",
      "photos": [
        "https://lh3.googleusercontent.com/d/1g5Ik0PfzIBEpDxffPHv7OK7xes6LJKKA",
        "https://lh3.googleusercontent.com/d/1_khm3NvUKr8CLmo0JXii6Z5uM3O8PIsf",
        "https://lh3.googleusercontent.com/d/11WIGVo-0QF1-TniNEyv5pSTjXP70kW9g"
      ]
    },
    {
      "name": "Laguna de Bay (Muntinlupa Part - Sucat)",
      "lat": 14.462758,
      "lon": 121.055639,
      "status": "Ongoing",
      "year started": "Pre-2004",
      "year completed": "N/A",
      "developer": "Local residents/establishments",
      "author": "AGF",
      "notes": "Mulltiple areas of reclaimation along the lakeshores of Barangay Sucat, Muntinlupa City. Starting point of the flood control dike projects.",
      "barangay": "Sucat",
      "municipality": "Muntinlupa City",
      "province": "Metro Manila",
      "region": "NCR",
      "address": "Sucat, Muntinlupa City, Metro Manila",
      "photos": [
        "https://lh3.googleusercontent.com/d/1msVTa9gIFQAyTI-1jF4_W237r2fgP8JR",
        "https://lh3.googleusercontent.com/d/1ZN19rIzNCmwcSpfyeIy8Pi4v79Cpet_g",
        "https://lh3.googleusercontent.com/d/15Jls4vXAFlqerkbKKjzoy9Ap6MDvru6u"
      ]
    },
    {
      "name": "Laguna de Bay (Muntinlupa Part - Cupang)",
      "lat": 14.431736,
      "lon": 121.051421,
      "status": "Ongoing",
      "year started": "Pre-2004",
      "year completed": "N/A",
      "developer": "Muntinlupa LGU",
      "author": "AGF",
      "notes": "Residential area, establishment, and public schools standing on reclaimed lands along the shores of barangay Cuupang.",
      "barangay": "Cupang",
      "municipality": "Muntinlupa City",
      "province": "Metro Manila",
      "region": "NCR",
      "address": "Cupang, Muntinlupa City, Metro Manila",
      "photos": [
        "https://lh3.googleusercontent.com/d/1Ltg8d4Hp8j3H4eodYVz-TOAq7N3uJvWw",
        "https://lh3.googleusercontent.com/d/1WPjQO7rszpZLTNlD8r9DvUdTbgPl9llC",
        "https://lh3.googleusercontent.com/d/12O-UvabYXvFFCvCrL3QuELvdnEZUnS5r"
      ]
    },
    {
      "name": "Alabang River Flood Control Embankment / Local Access Road",
      "lat": 14.424894,
      "lon": 121.052455,
      "status": "Completed",
      "year started": "2018",
      "year completed": "2024",
      "developer": "Muntinlupa LGU",
      "author": "AGF",
      "notes": "A flood-control embankment and an access road along the mouth of Alabang River and the lakeshores of Laguna de Bay",
      "barangay": "Cupang & Alabang",
      "municipality": "Muntinlupa City",
      "province": "Metro Manila",
      "region": "NCR",
      "address": "Cupang & Alabang, Muntinlupa City, Metro Manila",
      "photos": [
        "https://lh3.googleusercontent.com/d/1O2RjYx5BuDEHKbupHRm0YR2zJ9vuRPK_",
        "https://lh3.googleusercontent.com/d/1erABsU_tV0th0ZUstjNH0KOdZXzMlcXx",
        "https://lh3.googleusercontent.com/d/1nH7oXBXtt4GUGhso6rMBqlYvtpBNxI97"
      ]
    },
    {
      "name": "Laguna de Bay (Muntinlupa Part - Alabang)",
      "lat": 14.418494,
      "lon": 121.052267,
      "status": "Ongoing",
      "year started": "Pre-2004",
      "year completed": "N/A",
      "developer": "Muntinlupa LGU",
      "author": "AGF",
      "notes": "Residential area built on reclaimed lands along the lakeshores of Alabang.",
      "barangay": "Alabang",
      "municipality": "Muntinlupa City",
      "province": "Metro Manila",
      "region": "NCR",
      "address": "Alabang, Muntinlupa City, Metro Manila",
      "photos": [
        "https://lh3.googleusercontent.com/d/1cQ49k2gR9SPII0upI93bakBcEbGflU08",
        "https://lh3.googleusercontent.com/d/1o8yiuYeMxlc7iOjCe8uEQfAxAZcDi0nC",
        "https://lh3.googleusercontent.com/d/1FCULUAF176weeEOshKVR3I0ugbKkFW6e"
      ]
    },
    {
      "name": "Laguna de Bay (Muntinlupa Part - Bayanan)",
      "lat": 14.413439,
      "lon": 121.052288,
      "status": "Ongoing",
      "year started": "2005",
      "year completed": "N/A",
      "developer": "Local Residents/Establishments",
      "author": "AGF",
      "notes": "Reclaimed area with residents and establishments as well as a small boat port.",
      "barangay": "Bayanan",
      "municipality": "Muntinlupa City",
      "province": "Metro Manila",
      "region": "NCR",
      "address": "Bayanan, Muntinlupa City, Metro Manila",
      "photos": [
        "https://lh3.googleusercontent.com/d/1E63W4Ld670yaWm4wRXUbvGXbbRwD-eS9",
        "https://lh3.googleusercontent.com/d/1W0DRQN9V-2bbURfk5U8ThpO-L2-qOHiu",
        "https://lh3.googleusercontent.com/d/1I0mJ6HLTW7psqB90C6xUuiGyLF4-9Shk"
      ]
    },
    {
      "name": "Laguna de Bay (Muntinlupa Part - Putatan)",
      "lat": 14.403217,
      "lon": 121.051419,
      "status": "Ongoing",
      "year started": "Pre-2005",
      "year completed": "N/A",
      "developer": "Local Residents/Establishments",
      "author": "AGF",
      "notes": "Reclaimed lands in the lakeshores of Laguna de Bay composed of residential house, establishments, and schools.",
      "barangay": "Putatan",
      "municipality": "Muntinlupa City",
      "province": "Metro Manila",
      "region": "NCR",
      "address": "Putatan, Muntinlupa City, Metro Manila",
      "photos": [
        "https://lh3.googleusercontent.com/d/1iHcXrhyadJbkcwyeFQrqvzDxhCO2O1ar",
        "https://lh3.googleusercontent.com/d/1m8al1N-82nluupdax3MtYAhWo5YByuwo",
        "https://lh3.googleusercontent.com/d/1icmkYJQzEKBV3xQmNSdVZwFpgCPe4Fc-"
      ]
    },
    {
      "name": "Barangay Putatan Flood Control Structure",
      "lat": 14.398131,
      "lon": 121.051495,
      "status": "Completed",
      "year started": "2022",
      "year completed": "2024",
      "developer": "DPWH & E. F. Chua Construction, Inc.",
      "author": "AGF",
      "notes": "Sea wall parallel to the coasts of Muntinlupa City (Brgy. Putatan).",
      "barangay": "Putatan",
      "municipality": "Muntinlupa City",
      "province": "Metro Manila",
      "region": "NCR",
      "address": "Putatan, Muntinlupa City, Metro Manila",
      "photos": [
        "https://lh3.googleusercontent.com/d/1FJMxfeak3g-xwqA261XFiq5TvpYtJPbO",
        "https://lh3.googleusercontent.com/d/1rgE9TcsOwUNIrrEyJ90-RBqke9D2OINf",
        "https://lh3.googleusercontent.com/d/1-LjNYt-BFvdY3GxKg511a6CWo8jCbF4k"
      ]
    },
    {
      "name": "Maynilad Water Intake Facility",
      "lat": 14.396702,
      "lon": 121.051855,
      "status": "Done",
      "year started": "2009",
      "year completed": "2019",
      "developer": "Metropolitan Waterworks and Sewerage System & Maynilad Water Services, Inc.",
      "author": "AGF",
      "notes": "A water intake/treatment facility in Muntinlupa that draws raw water from Laguna de Bay with a small service dock.",
      "barangay": "Putatan",
      "municipality": "Muntinlupa City",
      "province": "Metro Manila",
      "region": "NCR",
      "address": "Putatan, Muntinlupa City, Metro Manila",
      "photos": [
        "https://lh3.googleusercontent.com/d/1DImeTPVI94wfRFWiJhoK4_1YGA123H2T",
        "https://lh3.googleusercontent.com/d/1ySqWG1v-kMto43yQtTPx0-6OP-sQPkhh",
        "https://lh3.googleusercontent.com/d/1_7IQkfgbxmczuCNNk54J2xr-wrQS6WBe"
      ]
    },
    {
      "name": "Maynilad Poblacion Water Treatment Plant",
      "lat": 14.388256,
      "lon": 121.052477,
      "status": "Completed",
      "year started": "2021",
      "year completed": "2023",
      "developer": "Maynilad Water Services, Inc., Acciona & DMCI Holdings",
      "author": "AGF",
      "notes": "A water treatment facility along the shores of Laguna de Bay in brgy. Poblacion, Muntinlupa City.",
      "barangay": "Poblacion",
      "municipality": "Muntinlupa City",
      "province": "Metro Manila",
      "region": "NCR",
      "address": "Poblacion, Muntinlupa City, Metro Manila",
      "photos": [
        "https://lh3.googleusercontent.com/d/1QhPrkIZ0WBUIV4pCmKzA9-Da5DsocyIB",
        "https://lh3.googleusercontent.com/d/1NudLYRLjVpUsT5r1_MsEOL2jmCjCI0hS",
        "https://lh3.googleusercontent.com/d/1bGOZbNsX2tnFjh4XZblMvccZ1VQugNBG"
      ]
    },
    {
      "name": "Laguna de Bay (Muntinlupa Part - Poblacion)",
      "lat": 14.386402,
      "lon": 121.053722,
      "status": "Ongoing",
      "year started": "2004",
      "year completed": "N/A",
      "developer": "Local Residents/Establsihments",
      "author": "AGF",
      "notes": "Residential area with local establishments built on extended land reclmations along the lakeshores of brgy. Poblacion, Muntinlupa City.",
      "barangay": "Poblacion",
      "municipality": "Muntinlupa City",
      "province": "Metro Manila",
      "region": "NCR",
      "address": "Poblacion, Muntinlupa City, Metro Manila",
      "photos": [
        "https://lh3.googleusercontent.com/d/1mvGjalma1Mq2d8MdhNRYvjvT0s8ps-1r",
        "https://lh3.googleusercontent.com/d/1Nf14TRRUB5WeSfA0aCS0Zpptu1DbT5-9",
        "https://lh3.googleusercontent.com/d/1B9qJ5EECwjeM2iHkaFPA7tsLxl8h-sCZ"
      ]
    },
    {
      "name": "Muntinlupa Sports Complex",
      "lat": 14.383775,
      "lon": 121.052764,
      "status": "Completed",
      "year started": "2006",
      "year completed": "2024",
      "developer": "Muntinlupa LGU",
      "author": "AGF",
      "notes": "A sports complex with a basketball court, track oval, and aquatic center at brgy.Tunasan, Muntinlupa City.",
      "barangay": "Tunasan",
      "municipality": "Muntinlupa City",
      "province": "Metro Manila",
      "region": "NCR",
      "address": "Tunasan, Muntinlupa City, Metro Manila",
      "photos": [
        "https://lh3.googleusercontent.com/d/1LucJOs9R9AeppCiWmeE-YRebnesWvwkb",
        "https://lh3.googleusercontent.com/d/1zlNXceR0NOs5PGED-CdxHQ9pLREugqtJ",
        "https://lh3.googleusercontent.com/d/1_I_bDUvdrx_0wJuI9mgZDhSX7CKDiq5q"
      ]
    },
    {
      "name": "Parola Stockyard",
      "lat": 14.532624,
      "lon": 121.107028,
      "status": "Completed",
      "year started": "2023",
      "year completed": "2025",
      "developer": "N/A",
      "author": "AGF",
      "notes": "A warehouse area build on farmlands filled with reclamation materials.",
      "barangay": "Santa Ana",
      "municipality": "Taytay",
      "province": "Rizal",
      "region": "IV-A CALABARZON",
      "address": "Santa Ana, Taytay, Rizal",
      "photos": [
        "https://lh3.googleusercontent.com/d/1U82csvTUAqS-EJxQ1deN9KUOCUPcK_88",
        "https://lh3.googleusercontent.com/d/1ttfobypS4xnbvxyQUBAhuQk-YWg0INDW",
        "https://lh3.googleusercontent.com/d/1Sjk6YE_WKDQcNfta21tv809iqsjhhHc8"
      ]
    },
    {
      "name": "PMRCIP Solid Disposal Site",
      "lat": 14.530499,
      "lon": 121.108744,
      "status": "Completed",
      "year started": "2021",
      "year completed": "2024",
      "developer": "DPWH, Build Build Build project & Toyo Construction Co. Ltd.",
      "author": "AGF",
      "notes": "A site assigned for the backfilling of materials obtained from dredging and excavation of the river bank and waterway. A small loading dock is also present in the area.",
      "barangay": "Santa Ana",
      "municipality": "Taytay",
      "province": "Rizal",
      "region": "IV-A CALABARZON",
      "address": "Santa Ana, Taytay, Rizal",
      "photos": [
        "https://lh3.googleusercontent.com/d/1Dt0l8hCqLdGYBPOgD_ns0v41_2ogKXKS",
        "https://lh3.googleusercontent.com/d/14sCgrUFMIT_2kmhq8w6Mz1RGxxnWttGH",
        "https://lh3.googleusercontent.com/d/176RlNhvOZwPkTkcX9ZB10dJmVDuCJaa4"
      ]
    },
    {
      "name": "Brgy. Santa Ana Lakeshore Built-up area",
      "lat": 14.527806,
      "lon": 121.111098,
      "status": "Ongoing",
      "year started": "2014",
      "year completed": "N/A",
      "developer": "Local Residents/Establishments",
      "author": "AGF",
      "notes": "Several houses and facilities built-up on swamp areas along the lakeshores of brgy. Santa Ana, Taytay.",
      "barangay": "Santa Ana",
      "municipality": "Taytay",
      "province": "Rizal",
      "region": "IV-A CALABARZON",
      "address": "Santa Ana, Taytay, Rizal",
      "photos": [
        "https://lh3.googleusercontent.com/d/1FGZCJHTL7AwMhEyHp0v_KZ3Mg-JZ8Qka",
        "https://lh3.googleusercontent.com/d/1so0lvVXKUN9P0UX8ps8cTFhQ02T4rF1n",
        "https://lh3.googleusercontent.com/d/1ynklOttibKfXheiZvH8N289fbyivP6V_"
      ]
    },
    {
      "name": "Barangay San Juan Landfill",
      "lat": 14.531875,
      "lon": 121.116887,
      "status": "Ongoing",
      "year started": "2023",
      "year completed": "N/A",
      "developer": "Taytay LGU",
      "author": "AGF",
      "notes": "Swamp area that was converted into a landfill with few residents.",
      "barangay": "San Juan",
      "municipality": "Taytay",
      "province": "Rizal",
      "region": "IV-A CALABARZON",
      "address": "San Juan, Taytay, Rizal",
      "photos": [
        "https://lh3.googleusercontent.com/d/1DwU7ucGi9wXSKrCCZ6R53AX_g5-q1Jn9",
        "https://lh3.googleusercontent.com/d/1FNFKLwqut29IJsBUV4Otl9AWpYPfky9S",
        "https://lh3.googleusercontent.com/d/1gNGGCEO7NE1tJ3JskEOm_rj5SJYoXLWO"
      ]
    },
    {
      "name": "Cainta River Reclamation",
      "lat": 14.539665,
      "lon": 121.11903,
      "status": "Ongoing",
      "year started": "Pre-2002",
      "year completed": "N/A",
      "developer": "Local Residents/Establishments",
      "author": "AGF",
      "notes": "Several residential areas and establishments sitting on top of a reclaimed swamp area in the Cainta River.",
      "barangay": "San Juan",
      "municipality": "Taytay",
      "province": "Rizal",
      "region": "IV-A CALABARZON",
      "address": "San Juan, Taytay, Rizal",
      "photos": [
        "https://lh3.googleusercontent.com/d/14x7vQCq5UbET0j9JkBj6Rr3jBg1Y4Y9N",
        "https://lh3.googleusercontent.com/d/1DPFbyuvLLXlZcrZe-QgiJjfJHf9A_aSI",
        "https://lh3.googleusercontent.com/d/19z6-bnKVY7kDFOIOmM4G6ubUuPFpzAmf"
      ]
    },
    {
      "name": "Laguna de Bay (Taytay Part - San Juan)",
      "lat": 14.535933,
      "lon": 121.132977,
      "status": "Ongoing",
      "year started": "2010",
      "year completed": "N/A",
      "developer": "Local Residents",
      "author": "AGF",
      "notes": "Area near the mouth of Marikina River with evident land reclamation developed to be a residential area.",
      "barangay": "San Juan",
      "municipality": "Taytay",
      "province": "Rizal",
      "region": "IV-A CALABARZON",
      "address": "San Juan, Taytay, Rizal",
      "photos": [
        "https://lh3.googleusercontent.com/d/1kuXmYLzhh7WFRXYaJK6HoJGFM3OLVnqS",
        "https://lh3.googleusercontent.com/d/1Bu4KDsBs5-cOnQsk1rxntfOm-Ds1Qliz",
        "https://lh3.googleusercontent.com/d/1BdgB_JBe83-pSKeTzXWNED5te0I_nAf_"
      ]
    },
    {
      "name": "Barangay Muzon Warehouse Zone",
      "lat": 14.533496,
      "lon": 121.136319,
      "status": "Ongoing",
      "year started": "2015",
      "year completed": "N/A",
      "developer": "Local Establishments",
      "author": "AGF",
      "notes": "Area near the mouth of Marikina river where sever establishments such as Jentec Cold Storage Taytay and Philippine Seven Taytay Warehouse are built on.",
      "barangay": "Muzon",
      "municipality": "Taytay",
      "province": "Rizal",
      "region": "IV-A CALABARZON",
      "address": "Muzon, Taytay, Rizal",
      "photos": [
        "https://lh3.googleusercontent.com/d/1xHnhK2MfQdqeyLoiQ_IYPboBFlQ1Q48J",
        "https://lh3.googleusercontent.com/d/1KCU1x8YF2TlXH1-xEjZg1JXZ6TMTZmYL",
        "https://lh3.googleusercontent.com/d/1t7By1Iwu_qmUJoFdKtYPFU5Ri7Y9FkTy"
      ]
    },
    {
      "name": "Captain Veloso Pier",
      "lat": 10.303181,
      "lon": 123.935814,
      "status": "Completed?",
      "year started": "2020",
      "year completed": "2025",
      "developer": "Private?",
      "author": "CLSA",
      "notes": "Port connected to CDR Gonzaga Causeway; built on sand",
      "barangay": "Looc",
      "municipality": "Lapu-Lapu City",
      "province": "Cebu",
      "region": "Central Visayas",
      "address": "Looc, Lapu-Lapu City, Cebu"
    },
    {
      "name": "Best Western Sandbar Resort",
      "lat": 10.253519,
      "lon": 123.960785,
      "status": "Completed?",
      "year started": "2013",
      "year completed": "2024",
      "developer": "Best Western Sandbar Resort",
      "author": "CLSA",
      "notes": "Resort with facilities such as water parks and infinity pools; built on reef?",
      "barangay": "Alegria",
      "municipality": "Cordova",
      "province": "Cebu",
      "region": "Central Visayas",
      "address": "Alegria, Cordova, Cebu"
    }
  ]
}
